mpl_visual_context/__init__.py
mpl_visual_context/_version.py
mpl_visual_context/artist_helper.py
mpl_visual_context/axes_helper.py
mpl_visual_context/axes_panel.py
mpl_visual_context/axes_panel_obsolete.py
mpl_visual_context/bezier_helper.py
mpl_visual_context/color_matrix.py
mpl_visual_context/example.py
mpl_visual_context/hls_helper.py
mpl_visual_context/image_box.py
mpl_visual_context/image_effect.py
mpl_visual_context/legend_helper.py
mpl_visual_context/misc.py
mpl_visual_context/mpl_fix.py
mpl_visual_context/old.py
mpl_visual_context/path_effects_container.py
mpl_visual_context/patheffect_locator.py
mpl_visual_context/patheffects.py
mpl_visual_context/patheffects_base.py
mpl_visual_context/patheffects_color.py
mpl_visual_context/patheffects_glow.py
mpl_visual_context/patheffects_image_box.py
mpl_visual_context/patheffects_image_effect.py
mpl_visual_context/patheffects_multicolor.py
mpl_visual_context/patheffects_path.py
mpl_visual_context/patheffects_shadow.py
mpl_visual_context/patheffects_transform.py
mpl_visual_context/pe_cyberfunk.py
mpl_visual_context/pe_value_from_image.py
mpl_visual_context/spreader.py
mpl_visual_context/transform_helper.py
mpl_visual_context/bezier_light_old/__init__.py
mpl_visual_context/bezier_light_old/_base.py
mpl_visual_context/bezier_light_old/curve.py
mpl_visual_context/bezier_light_old/hazmat_curve_helpers.py
mpl_visual_context/bezier_light_old/hazmat_helpers.py
mpl_visual_context/bezier_lite/__init__.py
mpl_visual_context/bezier_lite/_base.py
mpl_visual_context/bezier_lite/curve.py
mpl_visual_context/bezier_lite/hazmat_curve_helpers.py
mpl_visual_context/bezier_lite/hazmat_helpers.py
mpl_visual_context/tests/__init__.py
mpl_visual_context/tests/test_example.py
mpl_visual_context-0.9.3.dist-info/LICENSE
mpl_visual_context-0.9.3.dist-info/METADATA
mpl_visual_context-0.9.3.dist-info/WHEEL
mpl_visual_context-0.9.3.dist-info/top_level.txt
mpl_visual_context-0.9.3.dist-info/RECORD
